{"nodes": [{"id": "f_antigravity_irc_workflow_test_integration_py", "label": "test_integration.py", "file_type": "code", "source_file": "test_integration.py", "source_location": "L1"}, {"id": "irc_workflow_test_integration_log", "label": "log()", "file_type": "code", "source_file": "test_integration.py", "source_location": "L6"}, {"id": "irc_workflow_test_integration_main", "label": "main()", "file_type": "code", "source_file": "test_integration.py", "source_location": "L9"}], "edges": [{"source": "f_antigravity_irc_workflow_test_integration_py", "target": "os", "relation": "imports", "context": "import", "confidence": "EXTRACTED", "source_file": "test_integration.py", "source_location": "L1", "weight": 1.0}, {"source": "f_antigravity_irc_workflow_test_integration_py", "target": "sys", "relation": "imports", "context": "import", "confidence": "EXTRACTED", "source_file": "test_integration.py", "source_location": "L2", "weight": 1.0}, {"source": "f_antigravity_irc_workflow_test_integration_py", "target": "json", "relation": "imports", "context": "import", "confidence": "EXTRACTED", "source_file": "test_integration.py", "source_location": "L3", "weight": 1.0}, {"source": "f_antigravity_irc_workflow_test_integration_py", "target": "subprocess", "relation": "imports", "context": "import", "confidence": "EXTRACTED", "source_file": "test_integration.py", "source_location": "L4", "weight": 1.0}, {"source": "f_antigravity_irc_workflow_test_integration_py", "target": "irc_workflow_test_integration_log", "relation": "contains", "confidence": "EXTRACTED", "source_file": "test_integration.py", "source_location": "L6", "weight": 1.0}, {"source": "f_antigravity_irc_workflow_test_integration_py", "target": "irc_workflow_test_integration_main", "relation": "contains", "confidence": "EXTRACTED", "source_file": "test_integration.py", "source_location": "L9", "weight": 1.0}, {"source": "irc_workflow_test_integration_main", "target": "irc_workflow_test_integration_log", "relation": "calls", "context": "call", "confidence": "EXTRACTED", "source_file": "test_integration.py", "source_location": "L22", "weight": 1.0}], "raw_calls": [{"caller_nid": "irc_workflow_test_integration_main", "callee": "dirname", "is_member_call": true, "source_file": "F:\\Antigravity\\IRC Workflow\\test_integration.py", "source_location": "L10"}, {"caller_nid": "irc_workflow_test_integration_main", "callee": "abspath", "is_member_call": true, "source_file": "F:\\Antigravity\\IRC Workflow\\test_integration.py", "source_location": "L10"}, {"caller_nid": "irc_workflow_test_integration_main", "callee": "join", "is_member_call": true, "source_file": "F:\\Antigravity\\IRC Workflow\\test_integration.py", "source_location": "L11"}, {"caller_nid": "irc_workflow_test_integration_main", "callee": "makedirs", "is_member_call": true, "source_file": "F:\\Antigravity\\IRC Workflow\\test_integration.py", "source_location": "L12"}, {"caller_nid": "irc_workflow_test_integration_main", "callee": "join", "is_member_call": true, "source_file": "F:\\Antigravity\\IRC Workflow\\test_integration.py", "source_location": "L14"}, {"caller_nid": "irc_workflow_test_integration_main", "callee": "join", "is_member_call": true, "source_file": "F:\\Antigravity\\IRC Workflow\\test_integration.py", "source_location": "L15"}, {"caller_nid": "irc_workflow_test_integration_main", "callee": "join", "is_member_call": true, "source_file": "F:\\Antigravity\\IRC Workflow\\test_integration.py", "source_location": "L16"}, {"caller_nid": "irc_workflow_test_integration_main", "callee": "join", "is_member_call": true, "source_file": "F:\\Antigravity\\IRC Workflow\\test_integration.py", "source_location": "L17"}, {"caller_nid": "irc_workflow_test_integration_main", "callee": "join", "is_member_call": true, "source_file": "F:\\Antigravity\\IRC Workflow\\test_integration.py", "source_location": "L18"}, {"caller_nid": "irc_workflow_test_integration_main", "callee": "write", "is_member_call": true, "source_file": "F:\\Antigravity\\IRC Workflow\\test_integration.py", "source_location": "L31"}, {"caller_nid": "irc_workflow_test_integration_main", "callee": "write", "is_member_call": true, "source_file": "F:\\Antigravity\\IRC Workflow\\test_integration.py", "source_location": "L39"}, {"caller_nid": "irc_workflow_test_integration_main", "callee": "write", "is_member_call": true, "source_file": "F:\\Antigravity\\IRC Workflow\\test_integration.py", "source_location": "L49"}, {"caller_nid": "irc_workflow_test_integration_main", "callee": "join", "is_member_call": true, "source_file": "F:\\Antigravity\\IRC Workflow\\test_integration.py", "source_location": "L55"}, {"caller_nid": "irc_workflow_test_integration_main", "callee": "copy", "is_member_call": true, "source_file": "F:\\Antigravity\\IRC Workflow\\test_integration.py", "source_location": "L65"}, {"caller_nid": "irc_workflow_test_integration_main", "callee": "run", "is_member_call": true, "source_file": "F:\\Antigravity\\IRC Workflow\\test_integration.py", "source_location": "L68"}, {"caller_nid": "irc_workflow_test_integration_main", "callee": "loads", "is_member_call": true, "source_file": "F:\\Antigravity\\IRC Workflow\\test_integration.py", "source_location": "L76"}, {"caller_nid": "irc_workflow_test_integration_main", "callee": "get", "is_member_call": true, "source_file": "F:\\Antigravity\\IRC Workflow\\test_integration.py", "source_location": "L77"}, {"caller_nid": "irc_workflow_test_integration_main", "callee": "exists", "is_member_call": true, "source_file": "F:\\Antigravity\\IRC Workflow\\test_integration.py", "source_location": "L83"}, {"caller_nid": "irc_workflow_test_integration_main", "callee": "load", "is_member_call": true, "source_file": "F:\\Antigravity\\IRC Workflow\\test_integration.py", "source_location": "L85"}, {"caller_nid": "irc_workflow_test_integration_main", "callee": "dump", "is_member_call": true, "source_file": "F:\\Antigravity\\IRC Workflow\\test_integration.py", "source_location": "L113"}, {"caller_nid": "irc_workflow_test_integration_main", "callee": "join", "is_member_call": true, "source_file": "F:\\Antigravity\\IRC Workflow\\test_integration.py", "source_location": "L117"}, {"caller_nid": "irc_workflow_test_integration_main", "callee": "run", "is_member_call": true, "source_file": "F:\\Antigravity\\IRC Workflow\\test_integration.py", "source_location": "L121"}, {"caller_nid": "irc_workflow_test_integration_main", "callee": "exists", "is_member_call": true, "source_file": "F:\\Antigravity\\IRC Workflow\\test_integration.py", "source_location": "L133"}, {"caller_nid": "irc_workflow_test_integration_main", "callee": "remove", "is_member_call": true, "source_file": "F:\\Antigravity\\IRC Workflow\\test_integration.py", "source_location": "L135"}]}